prematricula/__init__.py
prematricula/config.py
prematricula/curso.py
prematricula/curso_carrera.py
prematricula/custom_http_adapter.py
prematricula/expediente.py
prematricula/funciones_consola.py
prematricula/funciones_curso.py
prematricula/funciones_expediente.py
prematricula/funciones_imprimir.py
prematricula/funciones_io.py
prematricula/funciones_memory_reader.py
prematricula/funciones_menu.py
prematricula/funciones_procesamiento_expediente.py
prematricula/funciones_semestre.py
prematricula/funciones_web_scraping.py
prematricula/funciones_xlsxwriter.py
prematricula/historial.py
prematricula/main.py
prematricula/main_listing_parser.py
prematricula/semestre.py
prematricula/student_parser.py
prematricula-0.0.7.dist-info/licenses/LICENSE
prematricula-0.0.7.dist-info/METADATA
prematricula-0.0.7.dist-info/WHEEL
prematricula-0.0.7.dist-info/entry_points.txt
prematricula-0.0.7.dist-info/top_level.txt
prematricula-0.0.7.dist-info/RECORD
