Metadata-Version: 2.4
Name: prematricula
Version: 0.0.7
Summary: Software de soporte de revisión de pre-matrículas para la escuela de ingeniería industrial
Author-email: Mauricio Andrés Zamora Hernández <mauricio.zamorahernandez.ucr@gmail.com>
Project-URL: Homepage, https://github.com/mauricio-zamora/prematricula
Project-URL: Bug Tracker, https://github.com/mauricio-zamora/prematricula/issues
Classifier: Programming Language :: Python :: 3
Classifier: License :: OSI Approved :: MIT License
Classifier: Operating System :: OS Independent
Classifier: Development Status :: 3 - Alpha
Classifier: Environment :: Console
Classifier: Intended Audience :: Education
Classifier: License :: OSI Approved :: MIT License
Classifier: Natural Language :: Spanish
Requires-Python: >=3.10
License-File: LICENSE
Requires-Dist: pyperclip
Requires-Dist: requests
Requires-Dist: termcolor
Requires-Dist: XlsxWriter
Dynamic: license-file
